django_gulp/__init__.py
django_gulp/management/__init__.py
django_gulp/management/commands/__init__.py
django_gulp/management/commands/collectstatic.py
django_gulp/management/commands/runserver.py
django_gulp/management/commands/runserver_mixin.py
django_gulp/management/commands/runserver_plus.py
django_gulp-4.1.0.dist-info/METADATA
django_gulp-4.1.0.dist-info/RECORD
django_gulp-4.1.0.dist-info/WHEEL
django_gulp-4.1.0.dist-info/pbr.json
django_gulp-4.1.0.dist-info/top_level.txt
